scalar_doc/__init__.py
scalar_doc/cli.py
scalar_doc/core.py
scalar_doc-0.1.8.dist-info/LICENSE
scalar_doc-0.1.8.dist-info/METADATA
scalar_doc-0.1.8.dist-info/WHEEL
scalar_doc-0.1.8.dist-info/entry_points.txt
scalar_doc-0.1.8.dist-info/RECORD
