Metadata-Version: 2.3
Name: scalar_doc
Version: 0.1.8
Summary: Render beautiful, customizable OpenAPI documentation with Scalar — directly from Python.
License: MIT
Keywords: openapi,documentation,scalar,fastapi,cli,sdk
Author: Iago B. Almeida
Author-email: iago.borba.almeida@maistodos.com.br
Requires-Python: >=3.12,<4.0
Classifier: Development Status :: 5 - Production/Stable
Classifier: Intended Audience :: Developers
Classifier: License :: OSI Approved :: MIT License
Classifier: Programming Language :: Python :: 3
Classifier: Programming Language :: Python :: 3.12
Classifier: Programming Language :: Python :: 3.13
Classifier: Topic :: Software Development :: Documentation
Project-URL: Homepage, https://iagobalmeida.github.io/scalar_doc
Project-URL: Repository, https://github.com/iagobalmeida/scalar_doc
